gamethis/__init__.py
gamethis/main.py
gamethis/scraper/__init__.py
gamethis/scraper/fitgirl.py
gamethis/utils/__init__.py
gamethis/utils/conversion.py
gamethis/utils/helpers.py
gamethis/utils/run.py
gamethis/utils/style.py
gamethis-0.1.0.dist-info/METADATA
gamethis-0.1.0.dist-info/WHEEL
gamethis-0.1.0.dist-info/entry_points.txt
gamethis-0.1.0.dist-info/top_level.txt
gamethis-0.1.0.dist-info/RECORD
