Metadata-Version: 2.4
Name: gamethis
Version: 0.1.0
Summary: Add your description here
Requires-Python: >=3.12
Requires-Dist: beautifulsoup4>=4.14.2
Requires-Dist: httpx>=0.28.1
Requires-Dist: magnet2torrent>=1.2.1
Requires-Dist: path>=17.1.1
Requires-Dist: questionary>=2.1.1
Requires-Dist: rich>=14.2.0
Requires-Dist: typer>=0.20.0
